universal_function_zsd/__init__.py
universal_function_zsd/universal_function.py
universal_function_zsd/universal_parameter.py
universal_function_zsd-1.5.2.dist-info/licenses/LICENSE
universal_function_zsd-1.5.2.dist-info/METADATA
universal_function_zsd-1.5.2.dist-info/WHEEL
universal_function_zsd-1.5.2.dist-info/top_level.txt
universal_function_zsd-1.5.2.dist-info/RECORD
