Metadata-Version: 2.4
Name: universal_function_zsd
Version: 1.5.2
Summary: 可用于大部分项目的通用型函数库
Author-email: Colin Zhang <zsd0830@163.com>
Classifier: Programming Language :: Python :: 3
Classifier: License :: OSI Approved :: MIT License
Classifier: Operating System :: OS Independent
Requires-Python: >=3.8
License-File: LICENSE
Dynamic: license-file
